dohq_common/__init__.py
dohq_common/exceptions.py
dohq_common/deps_txt/__init__.py
dohq_common/deps_txt/deps_txt_lock_list_formatter.py
dohq_common/deps_txt/deps_txt_simple.py
dohq_common/package_parsers/__init__.py
dohq_common/package_parsers/debian_package_name_parser.py
dohq_common-1.0.25.dist-info/LICENSE
dohq_common-1.0.25.dist-info/METADATA
dohq_common-1.0.25.dist-info/WHEEL
dohq_common-1.0.25.dist-info/top_level.txt
dohq_common-1.0.25.dist-info/zip-safe
dohq_common-1.0.25.dist-info/RECORD
