Metadata-Version: 2.1
Name: dohq-common
Version: 1.0.25
Summary: Common libs for devopshq tools
Home-page: https://devopshq.github.io/common/
Author: Open DevOps Community
Author-email: devopshq@gmail.com
License: MIT
Download-URL: https://github.com/devopshq/common.git
Keywords: DevOpsHQ,devops
Platform: UNKNOWN
Classifier: Development Status :: 5 - Production/Stable
Classifier: Environment :: Console
Classifier: Intended Audience :: Developers
Classifier: Topic :: Utilities
Classifier: License :: OSI Approved :: MIT License
Classifier: Natural Language :: Russian
Classifier: Programming Language :: Python :: 3.7
